concurrent_loop/__init__.py
concurrent_loop/base.py
concurrent_loop/loops.py
concurrent_loop-1.1.4.dist-info/LICENSE
concurrent_loop-1.1.4.dist-info/METADATA
concurrent_loop-1.1.4.dist-info/WHEEL
concurrent_loop-1.1.4.dist-info/top_level.txt
concurrent_loop-1.1.4.dist-info/RECORD
