Metadata-Version: 2.1
Name: concurrent-loop
Version: 1.1.4
Summary: Helper for running functions in a concurrent loop.
Author-email: KC Lee <lathe-rebuke.0c@icloud.com>
Project-URL: Homepage, https://bitbucket.org/kclee/concurrent/src/master/
Classifier: Programming Language :: Python :: 3
Classifier: License :: OSI Approved :: GNU General Public License v3 (GPLv3)
Classifier: Operating System :: OS Independent
Requires-Python: >=3.7
License-File: LICENSE
